{"starList": [["Jack Nicholson", "Interest"]], "seriesList": [["South Park", "Interest"], ["Friends", "Interest"], ["Lost, les disparus", "Interest"], ["Les Simpson", "Interest"], ["Prison Break", "Interest"]], "movieList": [["Blow", "5"], ["Retour vers le futur", "5"], ["Retour vers le futur II", "5"], ["Le Seigneur des anneaux : la communaut\u00e9 de l\u2019anneau", "5"], ["Retour vers le futur III", "5"], ["Le Seigneur des anneaux : les deux tours", "5"], ["Le Seigneur des anneaux : le retour du roi", "5"], ["Deux fr\u00e8res", "5"], ["Le Fabuleux destin d\u2019Am\u00e9lie Poulain", "5"], ["La Vie est belle", "5"], ["Les Noces fun\u00e8bres", "5"], ["Sleepy Hollow, la l\u00e9gende du cavalier sans t\u00eate", "5"], ["From Hell", "5"], ["Neverland", "5"], ["Edward aux mains d\u2019argent", "5"], ["Fen\u00eatre secr\u00e8te", "5"], ["Charlie et la chocolaterie", "5"], ["Pirates des Cara\u00efbes : le Secret du Coffre Maudit", "5"], ["Pirates des Cara\u00efbes : Jusqu\u2019au Bout du Monde", "5"], ["Pirates des Cara\u00efbes : la Mal\u00e9diction du Black Pearl", "5"], ["Dead Man", "5"], ["La Neuvi\u00e8me porte", "5"], ["Rochester, le dernier des libertins", "5"], ["Mars Attacks!", "4"], ["C\u2019est arriv\u00e9 pr\u00e8s de chez vous", "4"], ["Le Boulet", "4"], ["Atomik Circus, le retour de James Bataille", "4"], ["Titanic", "4"], ["L\u2019Etrange No\u00ebl de M. Jack", "4"], ["Desperado 2 - Il \u00e9tait une fois au Mexique", "4"], ["Gilbert Grape", "4"], ["Cry-Baby", "4"], ["Las Vegas parano", "Interest"], ["Mr. & Mrs. Smith", "Interest"], ["Le Chocolat", "Interest"], ["Harry Potter et la chambre des secrets", "Interest"], ["Harry Potter et la Coupe de Feu", "Interest"], ["Harry Potter \u00e0 l\u2019\u00e9cole des sorciers", "Interest"], ["Harry Potter et le Prisonnier d\u2019Azkaban", "Interest"], ["Star Wars : Episode IV - Un nouvel espoir (La Guerre des \u00e9toiles)", "Interest"], ["Star Wars : Episode III - La Revanche des Sith", "Interest"], ["Le Pianiste", "Interest"], ["Domino", "Interest"], ["Intrusion", "Interest"], ["Sweeney Todd, le diabolique barbier de Fleet Street", "Interest"]], "name": "margosparrow", "id": "Z20070412170344270432577"}